qinglong_openapi-0.0.1.dist-info/licenses/LICENSE
qlapi/__init__.py
qlapi/ql.py
qlapi/ql_config.py
qlapi/ql_dependence.py
qlapi/ql_env.py
qlapi/ql_log.py
qlapi/ql_script.py
qlapi/ql_system.py
qlapi/ql_task.py
qinglong_openapi-0.0.1.dist-info/METADATA
qinglong_openapi-0.0.1.dist-info/WHEEL
qinglong_openapi-0.0.1.dist-info/top_level.txt
qinglong_openapi-0.0.1.dist-info/RECORD
