Metadata-Version: 2.4
Name: qinglong-openapi
Version: 0.0.1
Summary: 青龙面板api SDK (修复port参数bug)
Home-page: https://github.com/todrfu/qinglong-api
Author: todrfu
Author-email: todrfu@gmail.com
Project-URL: Bug Tracker, https://github.com/todrfu/qinglong-api/issues
Project-URL: Original Project, https://github.com/yuxian158/qinglong-api
Classifier: Programming Language :: Python :: 3
Classifier: License :: OSI Approved :: MIT License
Classifier: Operating System :: OS Independent
Requires-Python: >=3.6
License-File: LICENSE
Requires-Dist: requests
Dynamic: license-file
